Metadata-Version: 2.1
Name: dowolna-nazwa
Version: 1.0.1
Summary: Pakiet testowy
Home-page: http://google.com
License: UNKNOWN
Platform: UNKNOWN
